{"v":"5.7.3","fr":60,"ip":180,"op":361,"w":55,"h":51,"nm":"04_Apostrof","ddd":0,"assets":[],"layers":[{"ddd":0,"ind":1,"ty":3,"nm":"Quote","sr":1,"ks":{"o":{"a":0,"k":100,"ix":11},"r":{"a":0,"k":0,"ix":10},"p":{"a":0,"k":[27.29,25.244,0],"ix":2},"a":{"a":0,"k":[0,0,0],"ix":1},"s":{"a":0,"k":[100,100,100],"ix":6}},"ao":0,"ip":0,"op":3600,"st":0,"bm":0},{"ddd":0,"ind":2,"ty":4,"nm":"Path 19","parent":1,"sr":1,"ks":{"o":{"a":0,"k":100,"ix":11},"r":{"a":0,"k":0,"ix":10},"p":{"a":0,"k":[0,0,0],"ix":2},"a":{"a":0,"k":[27.29,25.244,0],"ix":1},"s":{"a":1,"k":[{"i":{"x":[0.3,0.3,0.3],"y":[1,1,1]},"o":{"x":[0.7,0.7,0.7],"y":[0,0,0]},"t":180,"s":[0,0,100]},{"i":{"x":[0.3,0.3,0.3],"y":[1,1,1]},"o":{"x":[0.7,0.7,0.7],"y":[0,0,0]},"t":224,"s":[100,100,100]},{"i":{"x":[0.3,0.3,0.3],"y":[1,1,1]},"o":{"x":[0.7,0.7,0.7],"y":[0,0,0]},"t":301,"s":[100,100,100]},{"t":345,"s":[0,0,100]}],"ix":6}},"ao":0,"shapes":[{"ty":"gr","it":[{"ind":0,"ty":"sh","ix":1,"ks":{"a":0,"k":{"i":[[0,0],[0,0],[0,0],[0,0],[-2.388,4.435],[-6.481,2.729],[0,0],[1.706,-3.07],[0,-6.14]],"o":[[0,0],[0,0],[0,0],[0,-9.211],[3.07,-5.458],[0,0],[-3.752,1.706],[-2.047,3.07],[0,0]],"v":[[20.127,28.655],[20.127,50.487],[0,50.487],[0,33.09],[3.411,12.622],[17.398,0],[22.173,7.505],[13.645,14.669],[10.575,28.655]],"c":true},"ix":2},"nm":"Path 1","mn":"ADBE Vector Shape - Group","hd":false},{"ind":1,"ty":"sh","ix":2,"ks":{"a":0,"k":{"i":[[0,0],[0,0],[0,0],[0,0],[-2.388,4.435],[-6.481,2.729],[0,0],[1.706,-3.07],[0.341,-6.14]],"o":[[0,0],[0,0],[0,0],[0,-9.552],[3.07,-5.458],[0,0],[-3.752,1.706],[-1.706,3.07],[0,0]],"v":[[52.875,28.655],[52.875,50.487],[32.749,50.487],[32.749,33.09],[36.16,12.622],[50.146,0],[54.581,7.505],[46.053,14.669],[42.982,28.655]],"c":true},"ix":2},"nm":"Path 2","mn":"ADBE Vector Shape - Group","hd":false},{"ty":"fl","c":{"a":0,"k":[0.988235294118,0.313725490196,0.458823529412,1],"ix":4},"o":{"a":0,"k":100,"ix":5},"r":1,"bm":0,"nm":"Fill 1","mn":"ADBE Vector Graphic - Fill","hd":false},{"ty":"tr","p":{"a":0,"k":[0,0],"ix":2},"a":{"a":0,"k":[0,0],"ix":1},"s":{"a":0,"k":[100,100],"ix":3},"r":{"a":0,"k":0,"ix":6},"o":{"a":0,"k":100,"ix":7},"sk":{"a":0,"k":0,"ix":4},"sa":{"a":0,"k":0,"ix":5},"nm":"Transform"}],"nm":"Path 19","np":4,"cix":2,"bm":0,"ix":1,"mn":"ADBE Vector Group","hd":false}],"ip":0,"op":3600,"st":0,"bm":0}],"markers":[]}